lambadalib/cmdline.py
lambadalib/codegen.py
lambadalib/functionproxy.py
lambadalib/lambada.py
lambadalib/netproxy.py
lambadalib/prelaunch.py
lambadatransformer-0.0.1.data/scripts/lambada
lambadatransformer-0.0.1.dist-info/DESCRIPTION.rst
lambadatransformer-0.0.1.dist-info/METADATA
lambadatransformer-0.0.1.dist-info/RECORD
lambadatransformer-0.0.1.dist-info/WHEEL
lambadatransformer-0.0.1.dist-info/metadata.json
lambadatransformer-0.0.1.dist-info/top_level.txt
