Metadata-Version: 2.0
Name: lambadatransformer
Version: 0.0.1
Summary: Lambada - Automated Deployment of Python Methods to the (Lambda) Cloud
Home-page: https://gitlab.com/josefspillner/lambada.git
Author: Josef Spillner
Author-email: josef.spillner@zhaw.ch
License: AGPL 3.0
Keywords: cloud faas serverless functions
Platform: UNKNOWN
Classifier: Development Status :: 2 - Pre-Alpha
Classifier: Environment :: Console
Classifier: Intended Audience :: Science/Research
Classifier: License :: OSI Approved :: GNU Affero General Public License v3
Classifier: Programming Language :: Python :: 3
Classifier: Topic :: Software Development :: Code Generators
